quackamollie/devtools/__init__.py
quackamollie/devtools/defaults.py
quackamollie/devtools/cli/__init__.py
quackamollie/devtools/cli/command/__init__.py
quackamollie/devtools/cli/command/db_schema_cli_command.py
quackamollie_devtools-0.1.dist-info/LICENSE
quackamollie_devtools-0.1.dist-info/METADATA
quackamollie_devtools-0.1.dist-info/WHEEL
quackamollie_devtools-0.1.dist-info/entry_points.txt
quackamollie_devtools-0.1.dist-info/top_level.txt
quackamollie_devtools-0.1.dist-info/RECORD
